odoo/addons/website_sale_product_minimal_price/README.rst
odoo/addons/website_sale_product_minimal_price/__init__.py
odoo/addons/website_sale_product_minimal_price/__manifest__.py
odoo/addons/website_sale_product_minimal_price/data/demo.xml
odoo/addons/website_sale_product_minimal_price/i18n/es.po
odoo/addons/website_sale_product_minimal_price/i18n/website_sale_product_minimal_price.pot
odoo/addons/website_sale_product_minimal_price/models/__init__.py
odoo/addons/website_sale_product_minimal_price/models/product_template.py
odoo/addons/website_sale_product_minimal_price/readme/CONTRIBUTORS.rst
odoo/addons/website_sale_product_minimal_price/readme/DESCRIPTION.rst
odoo/addons/website_sale_product_minimal_price/readme/USAGE.rst
odoo/addons/website_sale_product_minimal_price/static/description/icon.png
odoo/addons/website_sale_product_minimal_price/static/description/index.html
odoo/addons/website_sale_product_minimal_price/static/src/js/website_sale_product_minimal_price_tour.js
odoo/addons/website_sale_product_minimal_price/tests/__init__.py
odoo/addons/website_sale_product_minimal_price/tests/test_website_sale_product_minimal_price.py
odoo/addons/website_sale_product_minimal_price/views/assets.xml
odoo/addons/website_sale_product_minimal_price/views/templates.xml
odoo11_addon_website_sale_product_minimal_price-11.0.1.0.0.99.dev4.dist-info/METADATA
odoo11_addon_website_sale_product_minimal_price-11.0.1.0.0.99.dev4.dist-info/WHEEL
odoo11_addon_website_sale_product_minimal_price-11.0.1.0.0.99.dev4.dist-info/top_level.txt
odoo11_addon_website_sale_product_minimal_price-11.0.1.0.0.99.dev4.dist-info/RECORD
